account/__init__.py
account/admin.py
account/auth_backends.py
account/compat.py
account/conf.py
account/context_processors.py
account/decorators.py
account/fields.py
account/forms.py
account/hooks.py
account/languages.py
account/managers.py
account/middleware.py
account/mixins.py
account/models.py
account/signals.py
account/timezones.py
account/urls.py
account/utils.py
account/views.py
account/locale/it/LC_MESSAGES/django.po
account/management/__init__.py
account/management/commands/__init__.py
account/management/commands/expunge_deleted.py
account/management/commands/user_password_expiry.py
account/management/commands/user_password_history.py
account/templatetags/__init__.py
account/templatetags/account_tags.py
artek_user_accounts-2.1.2.dist-info/LICENSE
artek_user_accounts-2.1.2.dist-info/METADATA
artek_user_accounts-2.1.2.dist-info/WHEEL
artek_user_accounts-2.1.2.dist-info/top_level.txt
artek_user_accounts-2.1.2.dist-info/RECORD
