Metadata-Version: 2.1
Name: artek-user-accounts
Version: 2.1.2
Summary: a Django user account app
Home-page: https://github.com/AHDCreative/django_user_accounts
Author: DarkArtek
Author-email: luca@ahd-creative.com
License: MIT
Platform: UNKNOWN
Classifier: Development Status :: 5 - Production/Stable
Classifier: Environment :: Web Environment
Classifier: Intended Audience :: Developers
Classifier: License :: OSI Approved :: MIT License
Classifier: Operating System :: OS Independent
Classifier: Programming Language :: Python
Classifier: Programming Language :: Python :: 3
Classifier: Framework :: Django
Requires-Dist: Django (>=1.11)
Requires-Dist: django-appconf (>=1.0.1)
Requires-Dist: pytz (>=2015.6)
Provides-Extra: pytest
Requires-Dist: pytest ; extra == 'pytest'
Requires-Dist: pytest-django ; extra == 'pytest'
